{
    "totalDemons": 181,
    "data": {
        "Kichijoji" : [
            {
                "id": 0,
                "name": "Pixie"
            },
            {
                "id": 1,
                "name": "Brownie"
            },
            {
                "id": 2,
                "name": "Ghost"
            },
            {
                "id": 3,
                "name": "Moryo"
            },
            {
                "id": 4,
                "name": "Yakuza"
            },
            {
                "id": 5,
                "name": "Thug"
            }
        ],
        "Arcade" : [
            {
                "id": 0,
                "name": "Pixie"
            },
            {
                "id": 1,
                "name": "Brownie"
            },
            {
                "id": 6,
                "name": "War Dog"
            },
            {
                "id": 7,
                "name": "Preta"
            },
            {
                "id": 8,
                "name": "Gran Battalion"
            },
            {
                "id": 9,
                "name": "Lady Zombie"
            },
            {
                "id": 10,
                "name": "Zombie"
            },
            {
                "id": 11,
                "name": "Kugutsu"
            }
        ],
        "Hospital" : [
            {
                "id": 0,
                "name": "Pixie"
            },
            {
                "id": 6,
                "name": "War Dog"
            }, {
                "id": 7,
                "name": "Preta"
            }, {
                "id": 10,
                "name": "Zombie"
            },
            {
                "id": 2,
                "name": "Ghost"
            },
            {
                "id": 12,
                "name": "Knocker"
            }
        ],
        "Echo Building" : [
            {
                "id": 13,
                "name": "Goblin"
            },
            {
                "id": 14,
                "name": "Andras"
            },
            {
                "id": 15,
                "name": "Kobold"
            },
            {
                "id": 12,
                "name": "Knocker"
            },
            {
                "id": 16,
                "name": "Gremlin"
            },
            {
                "id": 7,
                "name": "Preta"
            }
        ],
        "Laboratory" : [
            {
                "id": 13,
                "name": "Goblin"
            },
            {
                "id": 14,
                "name": "Andras"
            },
            {
                "id": 15,
                "name": "Kobold"
            },
            {
                "id": 12,
                "name": "Knocker"
            },
            {
                "id": 16,
                "name": "Gremlin"
            },
            {
                "id": 7,
                "name": "Preta"
            }
        ],
        "Shinjuku" : [
            {
                "id": 17,
                "name": "Imp"
            },
            {
                "id": 18,
                "name": "Jack Lantern"
            },
            {
                "id": 19,
                "name": "Jack Frost"
            },
            {
                "id": 13,
                "name": "Goblin"
            },
            {
                "id": 14,
                "name": "Andras"
            },
            {
                "id": 15,
                "name": "Kobold"
            },
            {
                "id": 20,
                "name": "Oshichi"
            },
            {
                "id": 7,
                "name": "Preta"
            },
            {
                "id": 2,
                "name": "Ghost"
            },
            {
                "id": 21,
                "name": "Bodyconian"
            },
            {
                "id": 10,
                "name": "Zombie"
            },
            {
                "id": 22,
                "name": "Slime"
            },
            {
                "id": 23,
                "name": "Yakuza"
            }
        ],
        "Tokyo Government Building" : [
            {
                "id": 17,
                "name": "Imp"
            },
            {
                "id": 18,
                "name": "Jack Lantern"
            },
            {
                "id": 19,
                "name": "Jack Frost"
            },
            {
                "id": 13,
                "name": "Goblin"
            },
            {
                "id": 14,
                "name": "Andras"
            },
            {
                "id": 15,
                "name": "Kobold"
            },
            {
                "id": 20,
                "name": "Oshichi"
            },
            {
                "id": 24,
                "name": "Gamigin"
            },
            {
                "id": 22,
                "name": "Slime"
            },
            {
                "id": 25,
                "name": "Dryad"
            }
        ],
        "Ozawa's Lair" :  [
            {
                "id": 17,
                "name": "Imp"
            },
            {
                "id": 18,
                "name": "Jack Lantern"
            },
            {
                "id": 19,
                "name": "Jack Frost"
            },
            {
                "id": 13,
                "name": "Goblin"
            }, {
                "id": 14,
                "name": "Andras"
            }, {
                "id": 15,
                "name": "Kobold"
            },
            {
                "id": 20,
                "name": "Oshichi"
            },
            {
                "id": 24,
                "name": "Gamigin"
            },
            {
                "id": 22,
                "name": "Slime"
            },
            {
                "id": 25,
                "name": "Dryad"
            }
        ],
        "Gotou's Lair" : [
            {
                "id": 25,
                "name": "Shade"
            },
            {
                "id": 26,
                "name": "Nue"
            },
            {
                "id": 17,
                "name": "Imp"
            },
            {
                "id": 24,
                "name": "Gamigin"
            },
            {
                "id": 14,
                "name": "Andras"
            },
            {
                "id": 27,
                "name": "Azumi"
            },
            {
                "id": 28,
                "name": "Zombie Army"
            },
            {
                "id": 29,
                "name": "Kamikaze Fighter"
            },
            {
                "id": 30,
                "name": "Lemures"
            }
        ],
        "American Embassy": [
            {
                "id": 31,
                "name": "Angel"
            },
            {
                "id": 32,
                "name": "Harpie"
            },
            {
                "id": 25,
                "name": "Dryad"
            },
            {
                "id": 33,
                "name": "Cu Sith"
            },
            {
                "id": 34,
                "name": "Spartoi"
            },
            {
                "id": 35,
                "name": "Fachan"
            },
            {
                "id": 36,
                "name": "Orc"
            },
            {
                "id": 28,
                "name": "Zombie Army"
            },
            {
                "id": 37,
                "name": "Tun Kou"
            },
            {
                "id": 38,
                "name": "Fukei"
            },
            {
                "id": 39,
                "name": "Sanki"
            },
            {
                "id": 40,
                "name": "Bogle"
            }
        ],
        "Kongou Shinkai" : [
            {
                "id": 41,
                "name": "Kinnari"
            },
            {
                "id": 43,
                "name": "Gandharva"
            },
            {
                "id": 44,
                "name": "Nekomata"
            },
            {
                "id": 27,
                "name": "Azumi"
            },
            {
                "id": 45,
                "name": "Bugaboo"
            },
            {
                "id": 46,
                "name": "Tsuchigumo"
            }
        ],
        "Apocalyptic Shinjuku" : [
            {
                "id": 47,
                "name": "Rusalka"
            },
            {
                "id": 48,
                "name": "Momunofu"
            },
            {
                "id": 49,
                "name": "War Cat"
            },
            {
                "id": 50,
                "name": "Fallen Priest"
            },
            {
                "id": 51,
                "name": "Man Eater"
            },
            {
                "id": 52,
                "name": "Ghoul"
            }, {
                "id": 30,
                "name": "Lemures"
            },
            {
                "id": 53,
                "name": "Corpse"
            }
        ],
        "Outside Shinjuku" : [
            {
                "id": 52,
                "name": "Ghoul"
            },
            {
                "id": 54,
                "name": "Berith"
            },{
                "id": 45,
                "name": "Bugaboo"
            },
            {
                "id": 55,
                "name": "Bit Ball"
            },
            {
                "id": 56,
                "name": "Kokakucho"
            },
            {
                "id": 57,
                "name": "Fanatic"
            },
            {
                "id": 58,
                "name": "Temple Knight"
            }
        ],
        "Outside Shibuya/Roppongi" : [
            {
                "id": 59,
                "name": "Kelpie"
            },
            {
                "id": 56,
                "name": "Kokakucho"
            },
            {
                "id": 45,
                "name": "Bugaboo"
            },
            {
                "id": 58,
                "name": "Temple Knight"
            },
            {
                "id": 57,
                "name": "Fanatic"
            },
            {
                "id": 60,
                "name": "T93G"
            },
            {
                "id": 55,
                "name": "Bit Ball"
            },
            {
                "id": 61,
                "name": "Hell Rider"
            },
            {
                "id": 62,
                "name": "Kamikaze Rider"
            }
        ],
        "Shibuya" : [
            {
                "id": 63,
                "name": "Lilim"
            },
            {
                "id": 64,
                "name": "Elf"
            },
            {
                "id": 47,
                "name": "Rusalka"
            },
            {
                "id": 65,
                "name": "Dwarf"
            },
            {
                "id": 49,
                "name": "War Cat"
            },
            {
                "id": 58,
                "name": "Temple Knight"
            },
            {
                "id": 57,
                "name": "Fanatic"
            },
            {
                "id": 51,
                "name": "Man Eater"
            }
        ],
        "Heroine's Mind" : [
            {
                "id": 66,
                "name": "Lamia"
            },
            {
                "id": 67,
                "name": "Apsaras"
            },
            {
                "id": 63,
                "name": "Lilim"
            },
            {
                "id": 68,
                "name": "Nightmare"
            },
            {
                "id": 59,
                "name": "Kelpie"
            },
            {
                "id": 69,
                "name": "Orobas"
            },
            {
                "id": 70,
                "name": "Yakshni"
            },
            {
                "id": 71,
                "name": "Furiae"
            },
            {
                "id": 51,
                "name": "Man Eater"
            },
            {
                "id": 72,
                "name": "Pisaca"
            },
            {
                "id": 30,
                "name": "Lemures"
            }
        ],
        "Roppongi" : [
            {
                "id": 73,
                "name": "Baykok"
            },
            {
                "id": 74,
                "name": "Larvae"
            },
            {
                "id": 51,
                "name": "Man Eater"
            },
            {
                "id": 52,
                "name": "Ghoul"
            },
            {
                "id": 75,
                "name": "Phantom"
            },
            {
                "id": 72,
                "name": "Pisaca"
            },
            {
                "id": 53,
                "name": "Corpse"
            },
            {
                "id": 21,
                "name": "Bodyconian"
            },
            {
                "id": 76,
                "name": "Battalion"
            },
            {
                "id": 9,
                "name": "Lady Zombie"
            },
            {
                "id": 10,
                "name": "Zombie"
            }
        ],
        "Outside Ginza/Shinagawa" : [
            {
                "id": 77,
                "name": "Stonka"
            },
            {
                "id": 58,
                "name": "Temple Knight"
            },
            {
                "id": 57,
                "name": "Fanatic"
            },
            {
                "id": 71,
                "name": "Furiae"
            },
            {
                "id": 78,
                "name": "Atsuyu"
            },
            {
                "id": 79,
                "name": "Wendigo"
            },
            {
                "id": 80,
                "name": "T95C/P"
            },
            {
                "id": 60,
                "name": "T93G"
            },
            {
                "id": 55,
                "name": "Bit Ball"
            },
            {
                "id": 81,
                "name": "Isora"
            },
            {
                "id": 82,
                "name": "Cockatrice"
            },
            {
                "id": 83,
                "name": "Magus"
            }
        ],
        "Underground Passageway" : [
            {
                "id": 84,
                "name": "Forneus"
            },
            {
                "id": 85,
                "name": "Tanki"
            },
            {
                "id": 86,
                "name": "Werewolf"
            },
            {
                "id": 79,
                "name": "Wendigo"
            },
            {
                "id": 87,
                "name": "Sawo Bahku"
            },
            {
                "id": 53,
                "name": "Corpse"
            }
        ],
        "Outside Ginza" : [
            {
                "id": 66,
                "name": "Lamia"
            },
            {
                "id": 88,
                "name": "Hobgoblin"
            },
            {
                "id": 89,
                "name": "Purski"
            },
            {
                "id": 70,
                "name": "Yakshni"
            },
            {
                "id": 90,
                "name": "Kawancha"
            },
            {
                "id": 65,
                "name": "Dwarf"
            },
            {
                "id": 83,
                "name": "Magus"
            },
            {
                "id": 73,
                "name": "Baykok"
            },
            {
                "id": 91,
                "name": "Black Ooze"
            }
        ],
        "Outside Zoushigaya" : [
            {
                "id": 92,
                "name": "Dakini"
            },
            {
                "id": 88,
                "name": "Hobgoblin"
            },
            {
                "id": 93,
                "name": "Decarabia"
            },
            {
                "id": 85,
                "name": "Tanki"
            },
            {
                "id": 86,
                "name": "Werewolf"
            },
            {
                "id": 53,
                "name": "Corpse"
            }
        ],
        "Ginza": [
            {
                "id": 94,
                "name": "Oni Jorou"
            },
            {
                "id": 92,
                "name": "Dakini"
            },
            {
                "id": 95,
                "name": "Loa"
            },
            {
                "id": 63,
                "name": "Lilim"
            },
            {
                "id": 88,
                "name": "Hobgoblin"
            },
            {
                "id": 93,
                "name": "Decarabia"
            },
            {
                "id": 84,
                "name": "Forneus"
            },
            {
                "id": 96,
                "name": "Naga Raja"
            },
            {
                "id": 85,
                "name": "Tanki"
            },
            {
                "id": 65,
                "name": "Dwarf"
            },
            {
                "id": 97,
                "name": "Worm"
            }
        ],
        "Police HQ": [
            {
                "id": 98,
                "name": "Watcher"
            },
            {
                "id": 99,
                "name": "T95D"
            },
            {
                "id": 80,
                "name": "T95C/P"
            },
            {
                "id": 60,
                "name": "T93G"
            },
            {
                "id": 55,
                "name": "Bit Ball"
            }
        ],
        "Shinagawa Passageway" : [
            {
                "id": 100,
                "name": "Taraka"
            },
            {
                "id": 95,
                "name": "Loa"
            },
            {
                "id": 101,
                "name": "Chulruk"
            },
            {
                "id": 102,
                "name": "Leonard"
            }
        ],
        "Shinagawa" : [
            {
                "id": 103,
                "name": "Ibaragi Douji"
            },
            {
                "id": 104,
                "name": "Lahke"
            },
            {
                "id": 93,
                "name": "Decarabia"
            }
        ],
        "Outside Ikebukuro" : [
            {
                "id": 105,
                "name": "Senri"
            },
            {
                "id": 88,
                "name": "Hobgoblin"
            },
            {
                "id": 106,
                "name": "Badb Catha"
            },
            {
                "id": 107,
                "name": "Orthros"
            },
            {
                "id": 103,
                "name": "Ibaragi Douji"
            }
        ],
        "Ikebukuro" : [
            {
                "id": 108,
                "name": "Onkot"
            }, {
                "id": 109,
                "name": "Mezuki"
            },
            {
                "id": 110,
                "name": "Gozuki"
            },
            {
                "id": 111,
                "name": "Turdak"
            },
            {
                "id": 112,
                "name": "Sarutahiko"
            },
            {
                "id": 113,
                "name": "Tamamo"
            },
            {
                "id": 101,
                "name": "Chulruk"
            }
        ],
        "Ueno" : [
            {
                "id": 114,
                "name": "Nyi Calon"
            },
            {
                "id": 115,
                "name": "Vetala"
            },
            {
                "id": 116,
                "name": "Nataku"
            },
            {
                "id": 117,
                "name": "Ose"
            },
            {
                "id": 118,
                "name": "Incubus"
            }
        ],
        "Outside TDL" : [
            {
                "id": 119,
                "name": "Tamazu"
            },
            {
                "id": 120,
                "name": "Marchosias"
            },
            {
                "id": 106,
                "name": "Badb Catha"
            },
            {
                "id": 107,
                "name": "Orthros"
            },
            {
                "id": 113,
                "name": "Tamamo"
            },
            {
                "id": 121,
                "name": "Raksha Lango"
            },
            {
                "id": 122,
                "name": "Basilisk"
            },
            {
                "id": 123,
                "name": "Giant"
            },
            {
                "id": 124,
                "name": "Gurr"
            }
        ],
        "TDL" : [
            {
                "id": 125,
                "name": "Wyrm"
            },
            {
                "id": 118,
                "name": "Incubus"
            },
            {
                "id": 126,
                "name": "Gorgon"
            },
            {
                "id": 100,
                "name": "Taraka"
            },
            {
                "id": 127,
                "name": "Chorozon"
            },
            {
                "id": 128,
                "name": "Succubus"
            },
            {
                "id": 120,
                "name": "Marchosias"
            },
            {
                "id": 123,
                "name": "Giant"
            },
            {
                "id": 122,
                "name": "Basilisk"
            },
            {
                "id": 129,
                "name": "Manticore"
            }
        ],
        "Divine Deities" : [
            {
                "id": 92,
                "name": "Dakini"
            },
            {
                "id": 130,
                "name": "Tengu"
            },
            {
                "id": 131,
                "name": "Yaksha"
            },
            {
                "id": 132,
                "name": "Shuten Douji"
            },
            {
                "id": 111,
                "name": "Turdak"
            },
            {
                "id": 133,
                "name": "Rakshasa"
            },
            {
                "id": 134,
                "name": "Sanni Yaka"
            }
        ],
        "Apocalypse Tokyo Building" : [
            {
                "id": 135,
                "name": "Vritra"
            },
            {
                "id": 136,
                "name": "Hauman"
            },
            {
                "id": 137,
                "name": "Ganesha"
            },
            {
                "id": 30,
                "name": "Lemures"
            },
            {
                "id": 108,
                "name": "Onkot"
            },
            {
                "id": 105,
                "name": "Senri"
            },
            {
                "id": 121,
                "name": "Raksha Lango"
            },
            {
                "id": 131,
                "name": "Yaksha"
            },
            {
                "id": 115,
                "name": "Vetala"
            },
            {
                "id": 138,
                "name": "Hariti"
            },
            {
                "id": 139,
                "name": "Scylla"
            },
            {
                "id": 140,
                "name": "Dark Priest"
            },
            {
                "id": 141,
                "name": "Legion"
            }
        ],
        "Outside Cathedral" : [
            {
                "id": 142,
                "name": "Siren"
            },
            {
                "id": 143,
                "name": "Gryphon"
            },
            {
                "id": 144,
                "name": "Hresvelgr"
            },
            {
                "id": 145,
                "name": "Barbegazi"
            },
            {
                "id": 124,
                "name": "Gurr"
            },
            {
                "id": 123,
                "name": "Giant"
            },
            {
                "id": 121,
                "name": "Raksha Lango"
            },
            {
                "id": 106,
                "name": "Badb Catha"
            }
        ],
        "Sugamu Prison" : [
            {
                "id": 146,
                "name": "Abaddon"
            },
            {
                "id": 147,
                "name": "Kinnara"
            },
            {
                "id": 148,
                "name": "Scanner"
            },
            {
                "id": 140,
                "name": "Dark Priest"
            },
            {
                "id": 149,
                "name": "Cyclops"
            },
            {
                "id": 139,
                "name": "Scylla"
            },
            {
                "id": 150,
                "name": "Mishaguji"
            },
            {
                "id": 132,
                "name": "Shuten Douji"
            },
            {
                "id": 151,
                "name": "Cerberus"
            },
            {
                "id": 113,
                "name": "Tamamo"
            }
        ],
        "Masakado's Lair" : [
            {
                "id": 152,
                "name": "Arahabaki"
            },
            {
                "id": 153,
                "name": "Nagasunehiko"
            }
        ],
        "Flooded Tokyo": [
            {
                "id": 154,
                "name": "Kraken"
            }
        ],
        "Cathedral B1f Northeast" : [
            {
                "id": 155,
                "name": "Genbu"
            }
        ],
        "Upper Cathedral" : [
            {
                "id": 156,
                "name": "Atlas"
            },
            {
                "id": 137,
                "name": "Ganesha"
            },
            {
                "id": 157,
                "name": "Cu Chulainn"
            },
            {
                "id": 158,
                "name": "Serpent"
            },
            {
                "id": 159,
                "name": "Tam Lin"
            },
            {
                "id": 160,
                "name": "Troll"
            },
            {
                "id": 161,
                "name": "Itzamna"
            },
            {
                "id": 162,
                "name": "Quetzacoatl"
            },
            {
                "id": 163,
                "name": "Tezcatlipoca"
            },
            {
                "id": 148,
                "name": "Scanner"
            },
            {
                "id": 164,
                "name": "Girimekhala"
            },
            {
                "id": 136,
                "name": "Hanuman"
            },
            {
                "id": 165,
                "name": "Yamata-no-Orochi"
            },
            {
                "id": 166,
                "name": "Senko"
            },
            {
                "id": 167,
                "name": "Fenrir"
            },
            {
                "id": 168,
                "name": "Orcus"
            },
            {
                "id": 169,
                "name": "Pendragon"
            },
            {
                "id": 170,
                "name": "Oberon"
            },
            {
                "id": 171,
                "name": "Toutetsu"
            }
        ],
        "Lower Cathedral" : [
            {
                "id": 156,
                "name": "Atlas"
            },
            {
                "id": 172,
                "name": "Yurlungur"
            },
            {
                "id": 173,
                "name": "Vampire"
            },
            {
                "id": 158,
                "name": "Serpent"
            },
            {
                "id": 146,
                "name": "Abaddon"
            },
            {
                "id": 174,
                "name": "Samael"
            },
            {
                "id": 175,
                "name": "Assassin"
            },
            {
                "id": 176,
                "name": "Rangda"
            },
            {
                "id": 128,
                "name": "Succubus"
            },
            {
                "id": 177,
                "name": "Lich"
            },
            {
                "id": 161,
                "name": "Itzamna"
            },
            {
                "id": 178,
                "name": "Fleurety"
            },
            {
                "id": 138,
                "name": "Hariti"
            },
            {
                "id": 165,
                "name": "Yamata-no-Orochi"
            },
            {
                "id": 179,
                "name": "Kali"
            },
            {
                "id": 180,
                "name": "Flauros"
            },
            {
                "id": 181,
                "name": "Fafnir"
            }
        ]


    }
}